{"v":"5.7.13","fr":120,"ip":0,"op":90,"w":100,"h":100,"nm":"12-mark-as-done_3","ddd":0,"assets":[],"layers":[{"ddd":0,"ind":1,"ty":4,"nm":"star partical 4","sr":1,"ks":{"o":{"a":1,"k":[{"i":{"x":[0.667],"y":[1]},"o":{"x":[0.297],"y":[0]},"t":49,"s":[0]},{"i":{"x":[0.815],"y":[1]},"o":{"x":[0.333],"y":[0]},"t":62,"s":[100]},{"t":77,"s":[0]}],"ix":11},"r":{"a":1,"k":[{"i":{"x":[0.833],"y":[1]},"o":{"x":[0.333],"y":[0]},"t":49,"s":[0]},{"t":77,"s":[360]}],"ix":10},"p":{"a":1,"k":[{"i":{"x":0.667,"y":1},"o":{"x":0.333,"y":0},"t":49,"s":[44.027,38.124,0],"to":[-14.667,-3.333,0],"ti":[9.439,7.005,0]},{"i":{"x":0.667,"y":1},"o":{"x":0.333,"y":0},"t":62,"s":[12.025,23.126,0],"to":[-10.951,-8.127,0],"ti":[-2.334,2.584,0]},{"t":77,"s":[2.777,-2.376,0]}],"ix":2,"l":2},"a":{"a":0,"k":[12.527,-7.376,0],"ix":1,"l":2},"s":{"a":1,"k":[{"i":{"x":[0.667,0.667,0.667],"y":[1,1,1]},"o":{"x":[0.297,0.297,0.297],"y":[0,0,0]},"t":49,"s":[140,140,100]},{"i":{"x":[0.815,0.815,0.815],"y":[1,1,1]},"o":{"x":[0.333,0.333,0.333],"y":[0,0,0]},"t":62,"s":[300,300,100]},{"t":77,"s":[70,70,100]}],"ix":6,"l":2}},"ao":0,"shapes":[{"ty":"gr","it":[{"ind":0,"ty":"sh","ix":1,"ks":{"a":0,"k":{"i":[[0,0],[0,0],[0,0],[0,0],[0,0],[0,0],[0,0],[0,0],[0,0],[0,0]],"o":[[0,0],[0,0],[0,0],[0,0],[0,0],[0,0],[0,0],[0,0],[0,0],[0,0]],"v":[[12.527,-9.182],[14.309,-10.119],[13.968,-8.134],[15.41,-6.729],[13.418,-6.44],[12.527,-4.634],[11.636,-6.44],[9.643,-6.729],[11.085,-8.134],[10.745,-10.119]],"c":true},"ix":2},"nm":"Path 1","mn":"ADBE Vector Shape - Group","hd":false},{"ty":"fl","c":{"a":0,"k":[1,1,1,1],"ix":4},"o":{"a":0,"k":100,"ix":5},"r":1,"bm":0,"nm":"Fill 1","mn":"ADBE Vector Graphic - Fill","hd":false},{"ty":"tr","p":{"a":0,"k":[0,0],"ix":2},"a":{"a":0,"k":[0,0],"ix":1},"s":{"a":0,"k":[100,100],"ix":3},"r":{"a":0,"k":0,"ix":6},"o":{"a":0,"k":100,"ix":7},"sk":{"a":0,"k":0,"ix":4},"sa":{"a":0,"k":0,"ix":5},"nm":"Transform"}],"nm":"Group 1","np":2,"cix":2,"bm":0,"ix":1,"mn":"ADBE Vector Group","hd":false}],"ip":49,"op":80,"st":49,"bm":0},{"ddd":0,"ind":2,"ty":4,"nm":"star partical 3","sr":1,"ks":{"o":{"a":1,"k":[{"i":{"x":[0.667],"y":[1]},"o":{"x":[0.297],"y":[0]},"t":49,"s":[0]},{"i":{"x":[0.815],"y":[1]},"o":{"x":[0.333],"y":[0]},"t":62,"s":[100]},{"t":77,"s":[0]}],"ix":11},"r":{"a":1,"k":[{"i":{"x":[0.833],"y":[1]},"o":{"x":[0.333],"y":[0]},"t":49,"s":[0]},{"t":77,"s":[360]}],"ix":10},"p":{"a":1,"k":[{"i":{"x":0.667,"y":1},"o":{"x":0.333,"y":0},"t":49,"s":[32.027,78.624,0],"to":[-2.917,-2.583,0],"ti":[8.691,-7.913,0]},{"i":{"x":0.667,"y":1},"o":{"x":0.333,"y":0},"t":62,"s":[8.275,83.876,0],"to":[-6.451,5.873,0],"ti":[-2.334,2.584,0]},{"t":77,"s":[-3.723,105.624,0]}],"ix":2,"l":2},"a":{"a":0,"k":[12.527,-7.376,0],"ix":1,"l":2},"s":{"a":1,"k":[{"i":{"x":[0.667,0.667,0.667],"y":[1,1,1]},"o":{"x":[0.297,0.297,0.297],"y":[0,0,0]},"t":49,"s":[140,140,100]},{"i":{"x":[0.815,0.815,0.815],"y":[1,1,1]},"o":{"x":[0.333,0.333,0.333],"y":[0,0,0]},"t":62,"s":[300,300,100]},{"t":77,"s":[70,70,100]}],"ix":6,"l":2}},"ao":0,"shapes":[{"ty":"gr","it":[{"ind":0,"ty":"sh","ix":1,"ks":{"a":0,"k":{"i":[[0,0],[0,0],[0,0],[0,0],[0,0],[0,0],[0,0],[0,0],[0,0],[0,0]],"o":[[0,0],[0,0],[0,0],[0,0],[0,0],[0,0],[0,0],[0,0],[0,0],[0,0]],"v":[[12.527,-9.182],[14.309,-10.119],[13.968,-8.134],[15.41,-6.729],[13.418,-6.44],[12.527,-4.634],[11.636,-6.44],[9.643,-6.729],[11.085,-8.134],[10.745,-10.119]],"c":true},"ix":2},"nm":"Path 1","mn":"ADBE Vector Shape - Group","hd":false},{"ty":"fl","c":{"a":0,"k":[1,1,1,1],"ix":4},"o":{"a":0,"k":100,"ix":5},"r":1,"bm":0,"nm":"Fill 1","mn":"ADBE Vector Graphic - Fill","hd":false},{"ty":"tr","p":{"a":0,"k":[0,0],"ix":2},"a":{"a":0,"k":[0,0],"ix":1},"s":{"a":0,"k":[100,100],"ix":3},"r":{"a":0,"k":0,"ix":6},"o":{"a":0,"k":100,"ix":7},"sk":{"a":0,"k":0,"ix":4},"sa":{"a":0,"k":0,"ix":5},"nm":"Transform"}],"nm":"Group 1","np":2,"cix":2,"bm":0,"ix":1,"mn":"ADBE Vector Group","hd":false}],"ip":49,"op":80,"st":49,"bm":0},{"ddd":0,"ind":3,"ty":4,"nm":"star partical 2","sr":1,"ks":{"o":{"a":1,"k":[{"i":{"x":[0.667],"y":[1]},"o":{"x":[0.297],"y":[0]},"t":49,"s":[0]},{"i":{"x":[0.815],"y":[1]},"o":{"x":[0.333],"y":[0]},"t":62,"s":[100]},{"t":77,"s":[0]}],"ix":11},"r":{"a":1,"k":[{"i":{"x":[0.833],"y":[1]},"o":{"x":[0.333],"y":[0]},"t":49,"s":[0]},{"t":77,"s":[360]}],"ix":10},"p":{"a":1,"k":[{"i":{"x":0.667,"y":1},"o":{"x":0.333,"y":0},"t":49,"s":[60.527,60.874,0],"to":[2.333,-2.583,0],"ti":[-11.208,-3.542,0]},{"i":{"x":0.667,"y":1},"o":{"x":0.333,"y":0},"t":62,"s":[88.025,66.126,0],"to":[8.299,2.623,0],"ti":[-2.334,2.584,0]},{"t":77,"s":[106.527,83.124,0]}],"ix":2,"l":2},"a":{"a":0,"k":[12.527,-7.376,0],"ix":1,"l":2},"s":{"a":1,"k":[{"i":{"x":[0.667,0.667,0.667],"y":[1,1,1]},"o":{"x":[0.297,0.297,0.297],"y":[0,0,0]},"t":49,"s":[140,140,100]},{"i":{"x":[0.815,0.815,0.815],"y":[1,1,1]},"o":{"x":[0.333,0.333,0.333],"y":[0,0,0]},"t":62,"s":[300,300,100]},{"t":77,"s":[70,70,100]}],"ix":6,"l":2}},"ao":0,"shapes":[{"ty":"gr","it":[{"ind":0,"ty":"sh","ix":1,"ks":{"a":0,"k":{"i":[[0,0],[0,0],[0,0],[0,0],[0,0],[0,0],[0,0],[0,0],[0,0],[0,0]],"o":[[0,0],[0,0],[0,0],[0,0],[0,0],[0,0],[0,0],[0,0],[0,0],[0,0]],"v":[[12.527,-9.182],[14.309,-10.119],[13.968,-8.134],[15.41,-6.729],[13.418,-6.44],[12.527,-4.634],[11.636,-6.44],[9.643,-6.729],[11.085,-8.134],[10.745,-10.119]],"c":true},"ix":2},"nm":"Path 1","mn":"ADBE Vector Shape - Group","hd":false},{"ty":"fl","c":{"a":0,"k":[1,1,1,1],"ix":4},"o":{"a":0,"k":100,"ix":5},"r":1,"bm":0,"nm":"Fill 1","mn":"ADBE Vector Graphic - Fill","hd":false},{"ty":"tr","p":{"a":0,"k":[0,0],"ix":2},"a":{"a":0,"k":[0,0],"ix":1},"s":{"a":0,"k":[100,100],"ix":3},"r":{"a":0,"k":0,"ix":6},"o":{"a":0,"k":100,"ix":7},"sk":{"a":0,"k":0,"ix":4},"sa":{"a":0,"k":0,"ix":5},"nm":"Transform"}],"nm":"Group 1","np":2,"cix":2,"bm":0,"ix":1,"mn":"ADBE Vector Group","hd":false}],"ip":49,"op":80,"st":49,"bm":0},{"ddd":0,"ind":4,"ty":4,"nm":"star partical","sr":1,"ks":{"o":{"a":1,"k":[{"i":{"x":[0.667],"y":[1]},"o":{"x":[0.297],"y":[0]},"t":49,"s":[0]},{"i":{"x":[0.815],"y":[1]},"o":{"x":[0.333],"y":[0]},"t":62,"s":[100]},{"t":77,"s":[0]}],"ix":11},"r":{"a":1,"k":[{"i":{"x":[0.833],"y":[1]},"o":{"x":[0.333],"y":[0]},"t":49,"s":[0]},{"t":77,"s":[360]}],"ix":10},"p":{"a":1,"k":[{"i":{"x":0.667,"y":1},"o":{"x":0.333,"y":0},"t":49,"s":[62.527,42.624,0],"to":[2.333,-2.583,0],"ti":[-5.833,6.458,0]},{"i":{"x":0.667,"y":1},"o":{"x":0.333,"y":0},"t":62,"s":[72.525,22.126,0],"to":[5.834,-6.459,0],"ti":[-2.334,2.584,0]},{"t":77,"s":[99.527,0.624,0]}],"ix":2,"l":2},"a":{"a":0,"k":[12.527,-7.376,0],"ix":1,"l":2},"s":{"a":1,"k":[{"i":{"x":[0.667,0.667,0.667],"y":[1,1,1]},"o":{"x":[0.297,0.297,0.297],"y":[0,0,0]},"t":49,"s":[140,140,100]},{"i":{"x":[0.815,0.815,0.815],"y":[1,1,1]},"o":{"x":[0.333,0.333,0.333],"y":[0,0,0]},"t":62,"s":[300,300,100]},{"t":77,"s":[70,70,100]}],"ix":6,"l":2}},"ao":0,"shapes":[{"ty":"gr","it":[{"ind":0,"ty":"sh","ix":1,"ks":{"a":0,"k":{"i":[[0,0],[0,0],[0,0],[0,0],[0,0],[0,0],[0,0],[0,0],[0,0],[0,0]],"o":[[0,0],[0,0],[0,0],[0,0],[0,0],[0,0],[0,0],[0,0],[0,0],[0,0]],"v":[[12.527,-9.182],[14.309,-10.119],[13.968,-8.134],[15.41,-6.729],[13.418,-6.44],[12.527,-4.634],[11.636,-6.44],[9.643,-6.729],[11.085,-8.134],[10.745,-10.119]],"c":true},"ix":2},"nm":"Path 1","mn":"ADBE Vector Shape - Group","hd":false},{"ty":"fl","c":{"a":0,"k":[1,1,1,1],"ix":4},"o":{"a":0,"k":100,"ix":5},"r":1,"bm":0,"nm":"Fill 1","mn":"ADBE Vector Graphic - Fill","hd":false},{"ty":"tr","p":{"a":0,"k":[0,0],"ix":2},"a":{"a":0,"k":[0,0],"ix":1},"s":{"a":0,"k":[100,100],"ix":3},"r":{"a":0,"k":0,"ix":6},"o":{"a":0,"k":100,"ix":7},"sk":{"a":0,"k":0,"ix":4},"sa":{"a":0,"k":0,"ix":5},"nm":"Transform"}],"nm":"Group 1","np":2,"cix":2,"bm":0,"ix":1,"mn":"ADBE Vector Group","hd":false}],"ip":49,"op":80,"st":49,"bm":0},{"ddd":0,"ind":5,"ty":4,"nm":"elips particle 4","sr":1,"ks":{"o":{"a":1,"k":[{"i":{"x":[0.667],"y":[1]},"o":{"x":[0.167],"y":[0]},"t":49,"s":[0]},{"i":{"x":[0.833],"y":[1]},"o":{"x":[0.333],"y":[0]},"t":62,"s":[100]},{"t":74,"s":[0]}],"ix":11},"r":{"a":0,"k":0,"ix":10},"p":{"a":1,"k":[{"i":{"x":0.667,"y":1},"o":{"x":0.167,"y":0},"t":49,"s":[48.64,50.624,0],"to":[7.375,9.375,0],"ti":[2.406,-12.268,0]},{"i":{"x":0.833,"y":1},"o":{"x":0.333,"y":0},"t":62,"s":[53.142,89.377,0],"to":[-1.427,7.279,0],"ti":[9.625,-2.125,0]},{"t":74,"s":[31.64,104.374,0]}],"ix":2,"l":2},"a":{"a":0,"k":[-10.86,-7.376,0],"ix":1,"l":2},"s":{"a":1,"k":[{"i":{"x":[0.667,0.667,0.667],"y":[1,1,1]},"o":{"x":[0.167,0.167,0.167],"y":[0,0,0]},"t":49,"s":[90,90,100]},{"i":{"x":[0.833,0.833,0.833],"y":[1,1,1]},"o":{"x":[0.333,0.333,0.333],"y":[0,0,0]},"t":62,"s":[130,130,100]},{"t":74,"s":[70,70,100]}],"ix":6,"l":2}},"ao":0,"shapes":[{"ty":"gr","it":[{"ind":0,"ty":"sh","ix":1,"ks":{"a":0,"k":{"i":[[0,-1.316],[1.316,0],[0,1.316],[-1.316,0]],"o":[[0,1.316],[-1.316,0],[0,-1.316],[1.316,0]],"v":[[-8.478,-7.376],[-10.86,-4.994],[-13.243,-7.376],[-10.86,-9.759]],"c":true},"ix":2},"nm":"Path 1","mn":"ADBE Vector Shape - Group","hd":false},{"ty":"fl","c":{"a":0,"k":[1,1,1,1],"ix":4},"o":{"a":0,"k":100,"ix":5},"r":1,"bm":0,"nm":"Fill 1","mn":"ADBE Vector Graphic - Fill","hd":false},{"ty":"tr","p":{"a":0,"k":[0,0],"ix":2},"a":{"a":0,"k":[0,0],"ix":1},"s":{"a":0,"k":[100,100],"ix":3},"r":{"a":0,"k":0,"ix":6},"o":{"a":0,"k":100,"ix":7},"sk":{"a":0,"k":0,"ix":4},"sa":{"a":0,"k":0,"ix":5},"nm":"Transform"}],"nm":"Group 1","np":2,"cix":2,"bm":0,"ix":1,"mn":"ADBE Vector Group","hd":false}],"ip":49,"op":80,"st":49,"bm":0},{"ddd":0,"ind":6,"ty":4,"nm":"elips particle 3","sr":1,"ks":{"o":{"a":1,"k":[{"i":{"x":[0.667],"y":[1]},"o":{"x":[0.167],"y":[0]},"t":49,"s":[0]},{"i":{"x":[0.833],"y":[1]},"o":{"x":[0.333],"y":[0]},"t":62,"s":[100]},{"t":77,"s":[0]}],"ix":11},"r":{"a":0,"k":0,"ix":10},"p":{"a":1,"k":[{"i":{"x":0.667,"y":1},"o":{"x":0.167,"y":0},"t":49,"s":[57.14,52.124,0],"to":[4.375,-6.125,0],"ti":[-5.6,10.653,0]},{"i":{"x":0.833,"y":1},"o":{"x":0.333,"y":0},"t":62,"s":[89.892,27.877,0],"to":[5.236,-9.96,0],"ti":[-1.875,13.875,0]},{"t":77,"s":[100.14,0.624,0]}],"ix":2,"l":2},"a":{"a":0,"k":[-10.86,-7.376,0],"ix":1,"l":2},"s":{"a":1,"k":[{"i":{"x":[0.667,0.667,0.667],"y":[1,1,1]},"o":{"x":[0.167,0.167,0.167],"y":[0,0,0]},"t":49,"s":[90,90,100]},{"i":{"x":[0.833,0.833,0.833],"y":[1,1,1]},"o":{"x":[0.333,0.333,0.333],"y":[0,0,0]},"t":62,"s":[130,130,100]},{"t":77,"s":[70,70,100]}],"ix":6,"l":2}},"ao":0,"shapes":[{"ty":"gr","it":[{"ind":0,"ty":"sh","ix":1,"ks":{"a":0,"k":{"i":[[0,-1.316],[1.316,0],[0,1.316],[-1.316,0]],"o":[[0,1.316],[-1.316,0],[0,-1.316],[1.316,0]],"v":[[-8.478,-7.376],[-10.86,-4.994],[-13.243,-7.376],[-10.86,-9.759]],"c":true},"ix":2},"nm":"Path 1","mn":"ADBE Vector Shape - Group","hd":false},{"ty":"fl","c":{"a":0,"k":[1,1,1,1],"ix":4},"o":{"a":0,"k":100,"ix":5},"r":1,"bm":0,"nm":"Fill 1","mn":"ADBE Vector Graphic - Fill","hd":false},{"ty":"tr","p":{"a":0,"k":[0,0],"ix":2},"a":{"a":0,"k":[0,0],"ix":1},"s":{"a":0,"k":[100,100],"ix":3},"r":{"a":0,"k":0,"ix":6},"o":{"a":0,"k":100,"ix":7},"sk":{"a":0,"k":0,"ix":4},"sa":{"a":0,"k":0,"ix":5},"nm":"Transform"}],"nm":"Group 1","np":2,"cix":2,"bm":0,"ix":1,"mn":"ADBE Vector Group","hd":false}],"ip":49,"op":80,"st":49,"bm":0},{"ddd":0,"ind":7,"ty":4,"nm":"elips particle 2","sr":1,"ks":{"o":{"a":1,"k":[{"i":{"x":[0.667],"y":[1]},"o":{"x":[0.167],"y":[0]},"t":49,"s":[0]},{"i":{"x":[0.833],"y":[1]},"o":{"x":[0.333],"y":[0]},"t":62,"s":[100]},{"t":79,"s":[0]}],"ix":11},"r":{"a":0,"k":0,"ix":10},"p":{"a":1,"k":[{"i":{"x":0.667,"y":1},"o":{"x":0.167,"y":0},"t":49,"s":[50.14,56.624,0],"to":[-5.125,1.375,0],"ti":[11.812,2.311,0]},{"i":{"x":0.833,"y":1},"o":{"x":0.333,"y":0},"t":62,"s":[12.892,63.877,0],"to":[-10.014,-1.96,0],"ti":[2.625,3.125,0]},{"t":79,"s":[-5.86,51.624,0]}],"ix":2,"l":2},"a":{"a":0,"k":[-10.86,-7.376,0],"ix":1,"l":2},"s":{"a":1,"k":[{"i":{"x":[0.667,0.667,0.667],"y":[1,1,1]},"o":{"x":[0.167,0.167,0.167],"y":[0,0,0]},"t":49,"s":[90,90,100]},{"i":{"x":[0.833,0.833,0.833],"y":[1,1,1]},"o":{"x":[0.333,0.333,0.333],"y":[0,0,0]},"t":62,"s":[130,130,100]},{"t":79,"s":[70,70,100]}],"ix":6,"l":2}},"ao":0,"shapes":[{"ty":"gr","it":[{"ind":0,"ty":"sh","ix":1,"ks":{"a":0,"k":{"i":[[0,-1.316],[1.316,0],[0,1.316],[-1.316,0]],"o":[[0,1.316],[-1.316,0],[0,-1.316],[1.316,0]],"v":[[-8.478,-7.376],[-10.86,-4.994],[-13.243,-7.376],[-10.86,-9.759]],"c":true},"ix":2},"nm":"Path 1","mn":"ADBE Vector Shape - Group","hd":false},{"ty":"fl","c":{"a":0,"k":[1,1,1,1],"ix":4},"o":{"a":0,"k":100,"ix":5},"r":1,"bm":0,"nm":"Fill 1","mn":"ADBE Vector Graphic - Fill","hd":false},{"ty":"tr","p":{"a":0,"k":[0,0],"ix":2},"a":{"a":0,"k":[0,0],"ix":1},"s":{"a":0,"k":[100,100],"ix":3},"r":{"a":0,"k":0,"ix":6},"o":{"a":0,"k":100,"ix":7},"sk":{"a":0,"k":0,"ix":4},"sa":{"a":0,"k":0,"ix":5},"nm":"Transform"}],"nm":"Group 1","np":2,"cix":2,"bm":0,"ix":1,"mn":"ADBE Vector Group","hd":false}],"ip":49,"op":80,"st":49,"bm":0},{"ddd":0,"ind":8,"ty":4,"nm":"elips particle","sr":1,"ks":{"o":{"a":1,"k":[{"i":{"x":[0.667],"y":[1]},"o":{"x":[0.167],"y":[0]},"t":49,"s":[0]},{"i":{"x":[0.833],"y":[1]},"o":{"x":[0.333],"y":[0]},"t":62,"s":[100]},{"t":75,"s":[0]}],"ix":11},"r":{"a":0,"k":0,"ix":10},"p":{"a":1,"k":[{"i":{"x":0.667,"y":1},"o":{"x":0.167,"y":0},"t":49,"s":[53.64,53.624,0],"to":[-2.625,-3.125,0],"ti":[0.401,10.194,0]},{"i":{"x":0.833,"y":1},"o":{"x":0.333,"y":0},"t":62,"s":[31.392,14.377,0],"to":[-0.563,-14.314,0],"ti":[-9.125,4.875,0]},{"t":75,"s":[44.39,-11.126,0]}],"ix":2,"l":2},"a":{"a":0,"k":[-10.86,-7.376,0],"ix":1,"l":2},"s":{"a":1,"k":[{"i":{"x":[0.667,0.667,0.667],"y":[1,1,1]},"o":{"x":[0.167,0.167,0.167],"y":[0,0,0]},"t":49,"s":[90,90,100]},{"i":{"x":[0.833,0.833,0.833],"y":[1,1,1]},"o":{"x":[0.333,0.333,0.333],"y":[0,0,0]},"t":62,"s":[130,130,100]},{"t":75,"s":[70,70,100]}],"ix":6,"l":2}},"ao":0,"shapes":[{"ty":"gr","it":[{"ind":0,"ty":"sh","ix":1,"ks":{"a":0,"k":{"i":[[0,-1.316],[1.316,0],[0,1.316],[-1.316,0]],"o":[[0,1.316],[-1.316,0],[0,-1.316],[1.316,0]],"v":[[-8.478,-7.376],[-10.86,-4.994],[-13.243,-7.376],[-10.86,-9.759]],"c":true},"ix":2},"nm":"Path 1","mn":"ADBE Vector Shape - Group","hd":false},{"ty":"fl","c":{"a":0,"k":[1,1,1,1],"ix":4},"o":{"a":0,"k":100,"ix":5},"r":1,"bm":0,"nm":"Fill 1","mn":"ADBE Vector Graphic - Fill","hd":false},{"ty":"tr","p":{"a":0,"k":[0,0],"ix":2},"a":{"a":0,"k":[0,0],"ix":1},"s":{"a":0,"k":[100,100],"ix":3},"r":{"a":0,"k":0,"ix":6},"o":{"a":0,"k":100,"ix":7},"sk":{"a":0,"k":0,"ix":4},"sa":{"a":0,"k":0,"ix":5},"nm":"Transform"}],"nm":"Group 1","np":2,"cix":2,"bm":0,"ix":1,"mn":"ADBE Vector Group","hd":false}],"ip":49,"op":80,"st":49,"bm":0},{"ddd":0,"ind":9,"ty":4,"nm":"Layer 4","sr":1,"ks":{"o":{"a":0,"k":100,"ix":11},"r":{"a":0,"k":0,"ix":10},"p":{"a":0,"k":[50,50,0],"ix":2,"l":2},"a":{"a":0,"k":[0,0,0],"ix":1,"l":2},"s":{"a":1,"k":[{"i":{"x":[0.833,0.833,0.833],"y":[1,1,1]},"o":{"x":[0.167,0.167,0.167],"y":[0,0,0]},"t":50,"s":[100,100,100]},{"i":{"x":[0.833,0.833,0.833],"y":[1,1,1]},"o":{"x":[0.167,0.167,0.167],"y":[0,0,0]},"t":59,"s":[85,85,100]},{"i":{"x":[0.833,0.833,0.833],"y":[1,1,1]},"o":{"x":[0.167,0.167,0.167],"y":[0,0,0]},"t":69,"s":[110,110,100]},{"i":{"x":[0.833,0.833,0.833],"y":[1,1,1]},"o":{"x":[0.167,0.167,0.167],"y":[0,0,0]},"t":77,"s":[95,95,100]},{"i":{"x":[0.833,0.833,0.833],"y":[1,1,1]},"o":{"x":[0.167,0.167,0.167],"y":[0,0,0]},"t":85,"s":[103,103,100]},{"t":90,"s":[100,100,100]}],"ix":6,"l":2}},"ao":0,"shapes":[{"ty":"gr","it":[{"ind":0,"ty":"sh","ix":1,"ks":{"a":0,"k":{"i":[[0,0],[0,0],[0,0]],"o":[[0,0],[0,0],[0,0]],"v":[[-41.212,6.904],[-18.34,29.776],[41.212,-29.776]],"c":false},"ix":2},"nm":"Path 1","mn":"ADBE Vector Shape - Group","hd":false},{"ty":"tm","s":{"a":0,"k":0,"ix":1},"e":{"a":1,"k":[{"i":{"x":[0.833],"y":[1]},"o":{"x":[0.333],"y":[0]},"t":0,"s":[100]},{"i":{"x":[0.833],"y":[1]},"o":{"x":[0.167],"y":[0]},"t":1,"s":[0]},{"i":{"x":[0.833],"y":[1]},"o":{"x":[0.167],"y":[0]},"t":32,"s":[0]},{"t":59,"s":[100]}],"ix":2},"o":{"a":0,"k":0,"ix":3},"m":1,"ix":2,"nm":"Trim Paths 1","mn":"ADBE Vector Filter - Trim","hd":false},{"ty":"st","c":{"a":0,"k":[1,1,1,1],"ix":3},"o":{"a":0,"k":100,"ix":4},"w":{"a":0,"k":4,"ix":5},"lc":2,"lj":2,"bm":0,"nm":"Stroke 1","mn":"ADBE Vector Graphic - Stroke","hd":false},{"ty":"tr","p":{"a":0,"k":[0,0],"ix":2},"a":{"a":0,"k":[0,0],"ix":1},"s":{"a":0,"k":[100,100],"ix":3},"r":{"a":0,"k":0,"ix":6},"o":{"a":0,"k":100,"ix":7},"sk":{"a":0,"k":0,"ix":4},"sa":{"a":0,"k":0,"ix":5},"nm":"Transform"}],"nm":"Group 1","np":3,"cix":2,"bm":0,"ix":1,"mn":"ADBE Vector Group","hd":false},{"ty":"gr","it":[{"ind":0,"ty":"sh","ix":1,"ks":{"a":0,"k":{"i":[[0,0],[0,2.359],[-23.141,0],[0,-23.141],[23.141,0],[3.3,19.846]],"o":[[-0.375,-2.252],[0,-23.141],[23.141,0],[0,23.141],[-20.782,0],[0,0]],"v":[[-41.331,6.924],[-41.9,0],[0,-41.9],[41.9,0],[0,41.9],[-41.331,6.924]],"c":false},"ix":2},"nm":"Path 1","mn":"ADBE Vector Shape - Group","hd":false},{"ty":"tm","s":{"a":1,"k":[{"i":{"x":[0.833],"y":[1]},"o":{"x":[0.333],"y":[0]},"t":32,"s":[0]},{"t":58,"s":[100]}],"ix":1},"e":{"a":1,"k":[{"i":{"x":[0.833],"y":[1]},"o":{"x":[0.333],"y":[0]},"t":0,"s":[0]},{"t":32,"s":[100]}],"ix":2},"o":{"a":0,"k":0,"ix":3},"m":1,"ix":2,"nm":"Trim Paths 1","mn":"ADBE Vector Filter - Trim","hd":false},{"ty":"st","c":{"a":0,"k":[1,1,1,1],"ix":3},"o":{"a":0,"k":100,"ix":4},"w":{"a":0,"k":4,"ix":5},"lc":2,"lj":2,"bm":0,"nm":"Stroke 1","mn":"ADBE Vector Graphic - Stroke","hd":false},{"ty":"tr","p":{"a":0,"k":[0,0],"ix":2},"a":{"a":0,"k":[0,0],"ix":1},"s":{"a":0,"k":[100,100],"ix":3},"r":{"a":0,"k":0,"ix":6},"o":{"a":1,"k":[{"i":{"x":[0.833],"y":[1]},"o":{"x":[0.333],"y":[0]},"t":0,"s":[0]},{"i":{"x":[0.833],"y":[1]},"o":{"x":[0.167],"y":[0]},"t":15,"s":[100]},{"i":{"x":[0.833],"y":[1]},"o":{"x":[0.167],"y":[0]},"t":43,"s":[100]},{"t":60,"s":[0]}],"ix":7},"sk":{"a":0,"k":0,"ix":4},"sa":{"a":0,"k":0,"ix":5},"nm":"Transform"}],"nm":"circle","np":3,"cix":2,"bm":0,"ix":2,"mn":"ADBE Vector Group","hd":false}],"ip":0,"op":120,"st":0,"bm":0}],"markers":[]}