{
  "v": "5.7.13",
  "fr": 120,
  "ip": 0,
  "op": 40,
  "w": 100,
  "h": 100,
  "nm": "20-heading-three",
  "ddd": 0,
  "assets": [],
  "layers": [
    {
      "ddd": 0,
      "ind": 1,
      "ty": 4,
      "nm": "Layer 3",
      "sr": 1,
      "ks": {
        "o": { "a": 0, "k": 100, "ix": 11 },
        "r": { "a": 0, "k": 0, "ix": 10 },
        "p": { "a": 0, "k": [50, 50, 0], "ix": 2, "l": 2 },
        "a": { "a": 0, "k": [0, 0, 0], "ix": 1, "l": 2 },
        "s": { "a": 0, "k": [100, 100, 100], "ix": 6, "l": 2 }
      },
      "ao": 0,
      "shapes": [
        {
          "ty": "gr",
          "it": [
            {
              "ind": 0,
              "ty": "sh",
              "ix": 1,
              "ks": {
                "a": 0,
                "k": {
                  "i": [
                    [0, 0],
                    [0, 0],
                    [0, 0],
                    [0, 0],
                    [0, 0],
                    [0, 0],
                    [0, 0],
                    [0, 0],
                    [0, 0],
                    [0, 0],
                    [0, 0],
                    [0, 0]
                  ],
                  "o": [
                    [0, 0],
                    [0, 0],
                    [0, 0],
                    [0, 0],
                    [0, 0],
                    [0, 0],
                    [0, 0],
                    [0, 0],
                    [0, 0],
                    [0, 0],
                    [0, 0],
                    [0, 0]
                  ],
                  "v": [
                    [-36.328, 25.5],
                    [-36.328, -25.292],
                    [-29.606, -25.292],
                    [-29.606, -4.435],
                    [-3.205, -4.435],
                    [-3.205, -25.292],
                    [3.516, -25.292],
                    [3.516, 25.5],
                    [-3.205, 25.5],
                    [-3.205, 1.559],
                    [-29.606, 1.559],
                    [-29.606, 25.5]
                  ],
                  "c": true
                },
                "ix": 2
              },
              "nm": "Path 1",
              "mn": "ADBE Vector Shape - Group",
              "hd": false
            },
            {
              "ty": "fl",
              "c": { "a": 0, "k": [1, 1, 1, 1], "ix": 4 },
              "o": { "a": 0, "k": 100, "ix": 5 },
              "r": 1,
              "bm": 0,
              "nm": "Fill 1",
              "mn": "ADBE Vector Graphic - Fill",
              "hd": false
            },
            {
              "ty": "tr",
              "p": { "a": 0, "k": [-17.5, -0.75], "ix": 2 },
              "a": { "a": 0, "k": [-17.5, -0.75], "ix": 1 },
              "s": { "a": 0, "k": [100, 100], "ix": 3 },
              "r": { "a": 0, "k": 0, "ix": 6 },
              "o": { "a": 0, "k": 100, "ix": 7 },
              "sk": { "a": 0, "k": 0, "ix": 4 },
              "sa": { "a": 0, "k": 0, "ix": 5 },
              "nm": "Transform"
            }
          ],
          "nm": "h",
          "np": 2,
          "cix": 2,
          "bm": 0,
          "ix": 1,
          "mn": "ADBE Vector Group",
          "hd": false
        },
        {
          "ty": "gr",
          "it": [
            {
              "ty": "gr",
              "it": [
                {
                  "ind": 0,
                  "ty": "sh",
                  "ix": 1,
                  "ks": {
                    "a": 0,
                    "k": {
                      "i": [
                        [0.416, 4.229],
                        [0, 0],
                        [-1.72, -1.56],
                        [-2.474, 0],
                        [-2.023, 2.036],
                        [0, 3.007],
                        [1.872, 1.863],
                        [2.89, 0],
                        [1.755, -0.459],
                        [0, 0],
                        [-0.256, 0],
                        [-2.127, 1.387],
                        [0, 2.89],
                        [1.547, 1.504],
                        [2.448, 0],
                        [1.616, -1.525],
                        [0.464, -3.05],
                        [0, 0],
                        [-2.704, 2.301],
                        [-4.021, 0],
                        [-2.335, -1.187],
                        [-1.235, -2.054],
                        [0, -2.309],
                        [1.179, -1.803],
                        [2.309, -1.062],
                        [-1.664, -2.184],
                        [0, -3.28],
                        [3.237, -3.085],
                        [4.944, 0],
                        [2.946, 2.66]
                      ],
                      "o": [
                        [0, 0],
                        [0.715, 3.536],
                        [1.72, 1.56],
                        [2.933, 0],
                        [2.023, -2.032],
                        [0, -2.864],
                        [-1.872, -1.859],
                        [-1.179, 0],
                        [0, 0],
                        [0.416, 0.048],
                        [2.656, 0],
                        [2.127, -1.387],
                        [0, -2.288],
                        [-1.547, -1.499],
                        [-2.426, 0],
                        [-1.616, 1.525],
                        [0, 0],
                        [0.763, -4.181],
                        [2.704, -2.296],
                        [2.773, 0],
                        [2.335, 1.192],
                        [1.235, 2.058],
                        [0, 2.197],
                        [-1.179, 1.803],
                        [3.003, 0.693],
                        [1.664, 2.184],
                        [0, 4.437],
                        [-3.237, 3.085],
                        [-4.459, 0],
                        [-2.946, -2.656]
                      ],
                      "v": [
                        [12.354, 12.11],
                        [18.594, 11.278],
                        [22.251, 18.922],
                        [28.542, 21.262],
                        [35.977, 18.211],
                        [39.011, 10.654],
                        [36.203, 3.566],
                        [29.062, 0.775],
                        [24.66, 1.468],
                        [25.353, -4.008],
                        [26.358, -3.939],
                        [33.534, -6.019],
                        [36.723, -12.432],
                        [34.4, -18.117],
                        [28.403, -20.37],
                        [22.337, -18.082],
                        [19.217, -11.218],
                        [12.978, -12.328],
                        [18.178, -22.051],
                        [28.265, -25.5],
                        [35.925, -23.715],
                        [41.281, -18.845],
                        [43.136, -12.293],
                        [41.368, -6.296],
                        [36.133, -1.998],
                        [43.136, 2.318],
                        [45.631, 10.516],
                        [40.778, 21.799],
                        [28.507, 26.426],
                        [17.398, 22.44]
                      ],
                      "c": true
                    },
                    "ix": 2
                  },
                  "nm": "Path 1",
                  "mn": "ADBE Vector Shape - Group",
                  "hd": false
                },
                {
                  "ty": "fl",
                  "c": { "a": 0, "k": [1, 1, 1, 1], "ix": 4 },
                  "o": { "a": 0, "k": 100, "ix": 5 },
                  "r": 1,
                  "bm": 0,
                  "nm": "Fill 1",
                  "mn": "ADBE Vector Graphic - Fill",
                  "hd": false
                },
                {
                  "ty": "tr",
                  "p": { "a": 0, "k": [0, 0], "ix": 2 },
                  "a": { "a": 0, "k": [0, 0], "ix": 1 },
                  "s": { "a": 0, "k": [100, 100], "ix": 3 },
                  "r": { "a": 0, "k": 0, "ix": 6 },
                  "o": { "a": 0, "k": 100, "ix": 7 },
                  "sk": { "a": 0, "k": 0, "ix": 4 },
                  "sa": { "a": 0, "k": 0, "ix": 5 },
                  "nm": "Transform"
                }
              ],
              "nm": "h5",
              "np": 2,
              "cix": 2,
              "bm": 0,
              "ix": 1,
              "mn": "ADBE Vector Group",
              "hd": false
            },
            {
              "ty": "gr",
              "it": [
                {
                  "ind": 0,
                  "ty": "sh",
                  "ix": 1,
                  "ks": {
                    "a": 0,
                    "k": {
                      "i": [
                        [0.416, 4.229],
                        [0, 0],
                        [-1.72, -1.56],
                        [-2.474, 0],
                        [-2.023, 2.036],
                        [0, 3.007],
                        [1.872, 1.863],
                        [2.89, 0],
                        [1.755, -0.459],
                        [0, 0],
                        [-0.256, 0],
                        [-2.127, 1.387],
                        [0, 2.89],
                        [1.547, 1.504],
                        [2.448, 0],
                        [1.616, -1.525],
                        [0.464, -3.05],
                        [0, 0],
                        [-2.704, 2.301],
                        [-4.021, 0],
                        [-2.335, -1.187],
                        [-1.235, -2.054],
                        [0, -2.309],
                        [1.179, -1.803],
                        [2.309, -1.062],
                        [-1.664, -2.184],
                        [0, -3.28],
                        [3.237, -3.085],
                        [4.944, 0],
                        [2.946, 2.66]
                      ],
                      "o": [
                        [0, 0],
                        [0.715, 3.536],
                        [1.72, 1.56],
                        [2.933, 0],
                        [2.023, -2.032],
                        [0, -2.864],
                        [-1.872, -1.859],
                        [-1.179, 0],
                        [0, 0],
                        [0.416, 0.048],
                        [2.656, 0],
                        [2.127, -1.387],
                        [0, -2.288],
                        [-1.547, -1.499],
                        [-2.426, 0],
                        [-1.616, 1.525],
                        [0, 0],
                        [0.763, -4.181],
                        [2.704, -2.296],
                        [2.773, 0],
                        [2.335, 1.192],
                        [1.235, 2.058],
                        [0, 2.197],
                        [-1.179, 1.803],
                        [3.003, 0.693],
                        [1.664, 2.184],
                        [0, 4.437],
                        [-3.237, 3.085],
                        [-4.459, 0],
                        [-2.946, -2.656]
                      ],
                      "v": [
                        [12.354, 12.11],
                        [18.594, 11.278],
                        [22.251, 18.922],
                        [28.542, 21.262],
                        [35.977, 18.211],
                        [39.011, 10.654],
                        [36.203, 3.566],
                        [29.062, 0.775],
                        [24.66, 1.468],
                        [25.353, -4.008],
                        [26.358, -3.939],
                        [33.534, -6.019],
                        [36.723, -12.432],
                        [34.4, -18.117],
                        [28.403, -20.37],
                        [22.337, -18.082],
                        [19.217, -11.218],
                        [12.978, -12.328],
                        [18.178, -22.051],
                        [28.265, -25.5],
                        [35.925, -23.715],
                        [41.281, -18.845],
                        [43.136, -12.293],
                        [41.368, -6.296],
                        [36.133, -1.998],
                        [43.136, 2.318],
                        [45.631, 10.516],
                        [40.778, 21.799],
                        [28.507, 26.426],
                        [17.398, 22.44]
                      ],
                      "c": true
                    },
                    "ix": 2
                  },
                  "nm": "Path 1",
                  "mn": "ADBE Vector Shape - Group",
                  "hd": false
                },
                {
                  "ty": "fl",
                  "c": { "a": 0, "k": [1, 1, 1, 1], "ix": 4 },
                  "o": { "a": 0, "k": 100, "ix": 5 },
                  "r": 1,
                  "bm": 0,
                  "nm": "Fill 1",
                  "mn": "ADBE Vector Graphic - Fill",
                  "hd": false
                },
                {
                  "ty": "tr",
                  "p": { "a": 0, "k": [0, 87], "ix": 2 },
                  "a": { "a": 0, "k": [0, 0], "ix": 1 },
                  "s": { "a": 0, "k": [100, 100], "ix": 3 },
                  "r": { "a": 0, "k": 0, "ix": 6 },
                  "o": { "a": 0, "k": 100, "ix": 7 },
                  "sk": { "a": 0, "k": 0, "ix": 4 },
                  "sa": { "a": 0, "k": 0, "ix": 5 },
                  "nm": "Transform"
                }
              ],
              "nm": "h4",
              "np": 2,
              "cix": 2,
              "bm": 0,
              "ix": 2,
              "mn": "ADBE Vector Group",
              "hd": false
            },
            {
              "ty": "tr",
              "p": {
                "a": 1,
                "k": [
                  {
                    "i": { "x": 0.667, "y": 1 },
                    "o": { "x": 0.333, "y": 0 },
                    "t": 0,
                    "s": [28.182, 43.993],
                    "to": [0, 0],
                    "ti": [0, 0]
                  },
                  {
                    "i": { "x": 0.667, "y": 1 },
                    "o": { "x": 0.333, "y": 0 },
                    "t": 26,
                    "s": [28.182, -56.007],
                    "to": [0, 0],
                    "ti": [0, 0]
                  },
                  { "t": 40, "s": [28.182, -44.007] }
                ],
                "ix": 2
              },
              "a": { "a": 0, "k": [28.993, 43.963], "ix": 1 },
              "s": { "a": 0, "k": [100, 100], "ix": 3 },
              "r": { "a": 0, "k": 0, "ix": 6 },
              "o": { "a": 0, "k": 100, "ix": 7 },
              "sk": { "a": 0, "k": 0, "ix": 4 },
              "sa": { "a": 0, "k": 0, "ix": 5 },
              "nm": "Transform"
            }
          ],
          "nm": "h3",
          "np": 2,
          "cix": 2,
          "bm": 0,
          "ix": 2,
          "mn": "ADBE Vector Group",
          "hd": false
        }
      ],
      "ip": 0,
      "op": 120,
      "st": 0,
      "bm": 0
    }
  ],
  "markers": []
}
